README.rst
setup.py
bin/chrisstoreclient
chrisstoreclient/__init__.py
chrisstoreclient/client.py
chrisstoreclient/exceptions.py
python_chrisstoreclient.egg-info/PKG-INFO
python_chrisstoreclient.egg-info/SOURCES.txt
python_chrisstoreclient.egg-info/dependency_links.txt
python_chrisstoreclient.egg-info/not-zip-safe
python_chrisstoreclient.egg-info/requires.txt
python_chrisstoreclient.egg-info/top_level.txt