Metadata-Version: 1.0
Name: python-chrisstoreclient
Version: 0.0.7
Summary: (Python) client for the ChRIS store API
Home-page: https://github.com/FNNDSC/python-chrisstoreclient
Author: FNNDSC
Author-email: dev@babymri.org
License: MIT
Platform: UNKNOWN
